pimoscope/__init__.py
pimoscope/__main__.py
pimoscope/ahat.py
pimoscope/ehat.py
pimoscope-0.1.dist-info/LICENSE
pimoscope-0.1.dist-info/METADATA
pimoscope-0.1.dist-info/WHEEL
pimoscope-0.1.dist-info/entry_points.txt
pimoscope-0.1.dist-info/top_level.txt
pimoscope-0.1.dist-info/RECORD
