Metadata-Version: 2.1
Name: pimoscope
Version: 0.1
Summary: Test equipment for Knilb.
Home-page: http://knilb.com
Author: nko
Author-email: nate@knilb.com
License: Apache
Platform: UNKNOWN
Classifier: License :: OSI Approved :: Apache Software License
Classifier: Programming Language :: Python :: 2.7
Classifier: Programming Language :: Python :: 3.8
Requires-Dist: knilb
Requires-Dist: bottle
Requires-Dist: automationhat
Requires-Dist: explorerhat
